websocketclient/__init__.py
websocketclient/client.py
websocketclient/config.py
websocketclient/handlers.py
websocketclient/management/__init__.py
websocketclient/management/commands/__init__.py
websocketclient/management/commands/runwebsocketclient.py
django_websocketclient-0.1.0.dist-info/LICENSE
django_websocketclient-0.1.0.dist-info/WHEEL
django_websocketclient-0.1.0.dist-info/METADATA
django_websocketclient-0.1.0.dist-info/RECORD
